EasyTSAD/.vscode/extensions.json
EasyTSAD/Controller/GlobalCfg.toml
EasyTSAD/Controller/PathManager.py
EasyTSAD/Controller/TSADController.py
EasyTSAD/Controller/__init__.py
EasyTSAD/Controller/logger.py
EasyTSAD/DataFactory/LoadData.py
EasyTSAD/DataFactory/MTSData.py
EasyTSAD/DataFactory/TSData.py
EasyTSAD/DataFactory/TorchDataSet/PredictWindow.py
EasyTSAD/DataFactory/TorchDataSet/ReconstructWindow.py
EasyTSAD/DataFactory/TorchDataSet/__init__.py
EasyTSAD/DataFactory/__init__.py
EasyTSAD/Evaluations/Metrics.py
EasyTSAD/Evaluations/Performance.py
EasyTSAD/Evaluations/Protocols/EventDetect.py
EasyTSAD/Evaluations/Protocols/EventF1PA.py
EasyTSAD/Evaluations/Protocols/EventKthF1PA.py
EasyTSAD/Evaluations/Protocols/EventKthPrcPA.py
EasyTSAD/Evaluations/Protocols/EventKthRocPA.py
EasyTSAD/Evaluations/Protocols/EventPrcPA.py
EasyTSAD/Evaluations/Protocols/EventRocPA.py
EasyTSAD/Evaluations/Protocols/PointAuprcPA.py
EasyTSAD/Evaluations/Protocols/PointAurocPA.py
EasyTSAD/Evaluations/Protocols/PointF1.py
EasyTSAD/Evaluations/Protocols/PointF1PA.py
EasyTSAD/Evaluations/Protocols/PointKthF1PA.py
EasyTSAD/Evaluations/Protocols/PointPrc.py
EasyTSAD/Evaluations/Protocols/PointRoc.py
EasyTSAD/Evaluations/Protocols/VUS.py
EasyTSAD/Evaluations/Protocols/__init__.py
EasyTSAD/Evaluations/__init__.py
EasyTSAD/Evaluations/utils.py
EasyTSAD/Exptools/EarlyStoppingTorch.py
EasyTSAD/Exptools/__init__.py
EasyTSAD/Methods/AE/AE.py
EasyTSAD/Methods/AE/__init__.py
EasyTSAD/Methods/AE/config.toml
EasyTSAD/Methods/AR/AR.py
EasyTSAD/Methods/AR/__init__.py
EasyTSAD/Methods/AR/config.toml
EasyTSAD/Methods/AnomalyTransformer/AnomalyTransformer.py
EasyTSAD/Methods/AnomalyTransformer/TSDataset.py
EasyTSAD/Methods/AnomalyTransformer/__init__.py
EasyTSAD/Methods/AnomalyTransformer/config.toml
EasyTSAD/Methods/DCdetector/DCdetector.py
EasyTSAD/Methods/DCdetector/Model.py
EasyTSAD/Methods/DCdetector/RevIN.py
EasyTSAD/Methods/DCdetector/TSDataset.py
EasyTSAD/Methods/DCdetector/__init__.py
easytsad-0.3.0.2.dist-info/LICENSE
easytsad-0.3.0.2.dist-info/METADATA
easytsad-0.3.0.2.dist-info/WHEEL
easytsad-0.3.0.2.dist-info/RECORD
